qis/__init__.py
qis/examples/bear_normal_bull_sharpe.py
qis/examples/best_returns.py
qis/examples/bootstrap_analysis.py
qis/examples/boxplot_conditional_returns.py
qis/examples/btc_asset_corr.py
qis/examples/constant_notional.py
qis/examples/constant_weight_portfolios.py
qis/examples/core/perf_bbg_prices.py
qis/examples/core/price_plots.py
qis/examples/core/us_election.py
qis/examples/credit_spreads.py
qis/examples/europe_futures.py
qis/examples/ewma_multifactor_regression.py
qis/examples/factsheets/multi_assets.py
qis/examples/factsheets/multi_strategy.py
qis/examples/factsheets/pyblogs_reports.py
qis/examples/factsheets/strategy.py
qis/examples/factsheets/strategy_benchmark.py
qis/examples/figure_2ax.py
qis/examples/generate_option_rolls.py
qis/examples/interpolation_infrequent_returns.py
qis/examples/leveraged_strategies.py
qis/examples/long_short.py
qis/examples/marginal_asset_contribution.py
qis/examples/momentum_indices.py
qis/examples/ohlc_vol_analysis.py
qis/examples/overnight_returns.py
qis/examples/perf_external_assets.py
qis/examples/readme_performances.py
qis/examples/risk_return_frontier.py
qis/examples/rolling_performance.py
qis/examples/seasonality.py
qis/examples/sharpe_vs_sortino.py
qis/examples/simulate_quant_strats.py
qis/examples/test_ewm.py
qis/examples/test_scatter.py
qis/examples/try_pybloqs.py
qis/examples/universe_corrs.py
qis/examples/vix_beta_to_equities_bonds.py
qis/examples/vix_conditional_returns.py
qis/examples/vix_spy_by_year.py
qis/examples/vix_tenor_analysis.py
qis/examples/vol_without_weekends.py
qis/file_utils.py
qis/local_path.py
qis/models/__init__.py
qis/models/linear/__init__.py
qis/models/linear/auto_corr.py
qis/models/linear/corr_cov_matrix.py
qis/models/linear/ewm.py
qis/models/linear/ewm_convolution.py
qis/models/linear/ewm_factors.py
qis/models/linear/ewm_winsor_outliers.py
qis/models/linear/pca.py
qis/models/linear/plot_correlations.py
qis/models/linear/ra_returns.py
qis/models/README.md
qis/models/stats/__init__.py
qis-3.2.30.dist-info/LICENSE.txt
qis-3.2.30.dist-info/METADATA
qis-3.2.30.dist-info/WHEEL
qis-3.2.30.dist-info/RECORD
